cbfa/__init__.py
cbfa/class_based.py
cbfa/py.typed
cbfa-0.0.7.dist-info/LICENSE
cbfa-0.0.7.dist-info/METADATA
cbfa-0.0.7.dist-info/WHEEL
cbfa-0.0.7.dist-info/top_level.txt
cbfa-0.0.7.dist-info/RECORD
